biem_helmholtz_sphere_ep/__init__.py
biem_helmholtz_sphere_ep/__main__.py
biem_helmholtz_sphere_ep/cli.py
biem_helmholtz_sphere_ep/main.py
biem_helmholtz_sphere_ep/py.typed
biem_helmholtz_sphere_ep-1.0.0.dist-info/licenses/LICENSE
biem_helmholtz_sphere_ep-1.0.0.dist-info/METADATA
biem_helmholtz_sphere_ep-1.0.0.dist-info/WHEEL
biem_helmholtz_sphere_ep-1.0.0.dist-info/entry_points.txt
biem_helmholtz_sphere_ep-1.0.0.dist-info/top_level.txt
biem_helmholtz_sphere_ep-1.0.0.dist-info/RECORD
